{
  "20250730_144517": {
    "id": "20250730_144517",
    "timestamp": "2025-07-30T14:45:17.581939",
    "description": "Pre-sync backup - 2025-07-30T09:15:11.817806",
    "index_size": 67629,
    "metadata_size": 37210,
    "files": {
      "index": "data/backups/20250730_144517/faiss_index.bin",
      "metadata": "data/backups/20250730_144517/case_metadata.json"
    }
  },
  "20250730_145023": {
    "id": "20250730_145023",
    "timestamp": "2025-07-30T14:50:23.168957",
    "description": "Pre-sync backup - 2025-07-30T09:20:18.238785",
    "index_size": 67629,
    "metadata_size": 37210,
    "files": {
      "index": "data/backups/20250730_145023/faiss_index.bin",
      "metadata": "data/backups/20250730_145023/case_metadata.json"
    }
  },
  "20250730_145528": {
    "id": "20250730_145528",
    "timestamp": "2025-07-30T14:55:28.931746",
    "description": "Pre-sync backup - 2025-07-30T09:25:23.509783",
    "index_size": 67629,
    "metadata_size": 37210,
    "files": {
      "index": "data/backups/20250730_145528/faiss_index.bin",
      "metadata": "data/backups/20250730_145528/case_metadata.json"
    }
  },
  "20250730_150034": {
    "id": "20250730_150034",
    "timestamp": "2025-07-30T15:00:34.524130",
    "description": "Pre-sync backup - 2025-07-30T09:30:29.396900",
    "index_size": 67629,
    "metadata_size": 37210,
    "files": {
      "index": "data/backups/20250730_150034/faiss_index.bin",
      "metadata": "data/backups/20250730_150034/case_metadata.json"
    }
  },
  "20250730_150539": {
    "id": "20250730_150539",
    "timestamp": "2025-07-30T15:05:39.892110",
    "description": "Pre-sync backup - 2025-07-30T09:35:34.879112",
    "index_size": 67629,
    "metadata_size": 37210,
    "files": {
      "index": "data/backups/20250730_150539/faiss_index.bin",
      "metadata": "data/backups/20250730_150539/case_metadata.json"
    }
  }
}